spam_api/__init__.py
spam_api/anti_spam.py
spam_api/app.py
spam_api/spam_detector_model.pkl
spam_api-0.3.dist-info/METADATA
spam_api-0.3.dist-info/WHEEL
spam_api-0.3.dist-info/entry_points.txt
spam_api-0.3.dist-info/top_level.txt
spam_api-0.3.dist-info/RECORD
