Metadata-Version: 2.1
Name: spam-api
Version: 0.3
Summary: API para la detección de spam usando machine learning
Home-page: https://github.com/limbow/spam-api
Author: Joaquin Vasquez
Author-email: joacovasquez0@gmail.com
Classifier: Programming Language :: Python :: 3
Classifier: Programming Language :: Python :: 3.8
Classifier: License :: OSI Approved :: MIT License
Requires-Dist: fastapi
Requires-Dist: uvicorn
Requires-Dist: scikit-learn
Requires-Dist: joblib
Requires-Dist: pandas
Requires-Dist: requests
Requires-Dist: python-multipart
